xcom_232i/XcomRS232.py
xcom_232i/__init__.py
xcom_232i/constants.py
xcom_232i/controller.py
xcom_232i-0.1.4.dist-info/LICENSE
xcom_232i-0.1.4.dist-info/WHEEL
xcom_232i-0.1.4.dist-info/METADATA
xcom_232i-0.1.4.dist-info/RECORD
